{
    "410": {
        "question": "새 건물은 14개의 창문이 필요하다. 정국은 이미 그 중 5개를 설치했다. 만약 각각의 창문을 설치하는 데 4시간이 걸린다면, 정국이 나머지를 설치하는 데 얼마나 걸릴까?"
    },
    "411": {
        "question": "지민은 건물에 있는 12개의 방을 칠해야 한다. 각 방은 페인트 칠하는 데 3시간이 걸린다. 만약 지민이가 이미 4개의 방을 칠했다면, 지민이는 나머지를 칠하는데 얼마나 더 걸릴까요?"
    },
    "412": {
        "question": "석진은 병에서 22개의 사과를 꺼낸다. 원래 병에는 57개의 사과가 있었다. 병에 사과가 몇 개 남았습니까?"
    },
    "413": {
        "question": "오늘 점심에는 6개의 케익을, 저녁에는 9개의 케익을 제공했습니다. 오늘은 케이크가 몇 개나 나왔나요?"
    },
    "414": {
        "question": "총 3명이 3.75달러를 균등하게 분담해야 한다. 한 사람당 얼마나 많은 돈을 받을 수 있을까요? 답을 소수점으로 작성하시오."
    },
    "415": {
        "question": "태형은 9개의 파란색 풍선을 가지고 있지만 그것들 중 2개를 잃어버렸다. 태형은 지금 얼마나 많은 파란 풍선을 가지고 있나요?"
    },
    "416": {
        "question": "정국은 45개의 휘파람을 가지고 있다. 그는 유나보다 32개의 휘파람을 더 가지고 있다. 유나는 얼마나 많은 휘파람을 가지고 있나요?"
    },
    "417": {
        "question": "만약 상자 안에 76개의 지우개가 있고 민영이 9개의 지우개를 더 넣는다면, 얼마나 많은 지우개가 상자 안에 있나요?"
    },
    "418": {
        "question": "5개의 꽃과 3개의 벌이 있습니다. 꽃보다 벌이 얼마나 적은가요?"
    },
    "419": {
        "question": "민영은 3달러를 가지고 있다. 민영은 캔디바를 1달러에 샀다. 민영은 돈이 얼마나 남았는가?"
    },
    "420": {
        "question": "미니 도서관은 또한 고전을 위한 섹션을 가지고 있다. 만약 유정이 각각의 저자가 33권의 책을 가지고 있는 6명의 고전 작가들의 컬렉션을 가지고 있다면, 유정은 고전 부분에서 얼마나 많은 책을 가지고 있는가?"
    },
    "421": {
        "question": "석진은 플래시 드라이브에 26개의 음악 파일과 36개의 비디오 파일을 가지고 있었다. 만약 석진이 48개의 파일을 삭제했다면, 얼마나 많은 파일이 여전히 석진의 플래시 드라이브에 있겠는가?"
    },
    "422": {
        "question": "호석은 지역 보육원에서 10% 할인 쿠폰을 사용한다. 진달래, 부가인빌라, 그리고 화분용 토양의 가방을 산 후, 호석의 총 가격은 217.95 달러이다. 쿠폰이 없었다면 호석은 얼마를 지불했을까요?"
    },
    "423": {
        "question": "호석은 17개의 크레파스를 가지고 있다. 정국은 6개의 크레파스를 가져간다. 호석은 몇 개의 크레파스가 남습니까?"
    },
    "424": {
        "question": "석진은 고양이 장난감으로 8.77달러를 지불했고, 남준은 20달러 지폐와 함께 10.97달러를 지불했다. 석진은 얼마나 많은 잔돈을 받았습니까?"
    },
    "425": {
        "question": "민영은 24박스를 팔았다. 케이스에 8박스가 들어갈 때, 민영은 몇 개의 케이스를 배달해야 하나요?"
    },
    "426": {
        "question": "유나의 선생님은 위대한 수학공부를 위해 금별을 준다. 어제, 유나는 6개의 금별을 얻었다. 오늘, 유나는 9개를 더 벌었습니다. 유나는 모두 몇 개의 금별을 얻었는가?"
    },
    "427": {
        "question": "유나는 7.6인치의 흰색 선을 그었다. 그리고 그는 3.3인치 길이의 파란색 선을 그었다. 흰색 줄이 파란색 줄보다 얼마나 기나요?"
    },
    "428": {
        "question": "유정의 고등학교는 올해 864개의 야구 경기를 했고, 유정은 395개의 게임에 참가했다. 유정은 얼마나 많은 야구 경기를 놓쳤습니까?"
    },
    "429": {
        "question": "만약 500장의 종이의 무게가 7파운드라면, 2장의 무게는 얼마일까요?"
    },
    "430": {
        "question": "3명의 친구들이 레스토랑에 들어갔다. 남준은 이미 닭날개 6개를 익혔는데 3개를 더 익혔다. 만약 닭날개들이 각각 같은 양을 받는다면 한 사람당 몇 개를 얻을 수 있을까?"
    },
    "431": {
        "question": "지민의 고등학교는 올해 64개의 축구 경기를 했다. 지민은 32개의 게임에 참가했다. 지민은 얼마나 많은 축구경기를 놓쳤습니까?"
    },
    "432": {
        "question": "한 회사에서 24명을 초청해서 오찬을 했는데 10명이 안 나왔는데 7명씩 들고 있던 테이블이 몇 개나 필요한가요?"
    },
    "433": {
        "question": "지난 토요일, 태형은 425개의 잡지와 275개의 신문을 팔았습니다. 태형이 판매한 독서 자료의 총 수는 몇 개입니까?"
    },
    "434": {
        "question": "은지는 40개의 뚜껑을 가지고 있다. 그는 7개를 더 산다. 은지는 총 몇 개의 병뚜껑을 가지고 있나요?"
    },
    "435": {
        "question": "남준은 41장의 사진을 페이스북에 올렸다. 남준은 한 앨범에 37개의 사진을 넣었다. 사진은 몇 장이 남습니까?"
    },
    "436": {
        "question": "태형은 과수원에서 자두 7개와 오렌지 4개를 땄다. 태형은 지민에게 3개의 자두를 주었다. 태형은 지금 몇 개의 자두를 가지고 있나?"
    },
    "437": {
        "question": "한 레스토랑은 오늘 점심에는 9개의 피자를, 저녁에는 6개의 피자를 제공했습니다. 오늘 얼마나 많은 피자가 나왔나요?"
    },
    "438": {
        "question": "호석은 병원에 있었고 전국에서 403장의 카드를 받았다. 호석이 집에 도착했을 때 호석은 친구들과 가족들로부터 287장의 카드를 더 받았다. 호석은 모두 몇 장의 카드를 받았는가?"
    },
    "439": {
        "question": "공원에는 현재 112그루의 짧은 나무와 119그루의 큰 나무가 있다. 공원 근로자들은 오늘 105그루의 짧은 나무를 심을 것이다. 일꾼들이 일을 마치면 공원에는 얼마나 많은 짧은 나무들이 있을 것인가?"
    },
    "440": {
        "question": "A의 0.5는 A의 0.16보다 10 더 많다. A를 찾아라. 답을 소수점으로 작성하시오."
    },
    "441": {
        "question": "작년에, 90171명의 사람들이 한 나라에서 태어났고, 16320명의 사람들이 그 나라로 이주했습니다. 작년에 얼마나 많은 사람들이 이 나라에 살기 시작했습니까?"
    },
    "442": {
        "question": "카니발에서 태형은 관람차를 5번, 범퍼카는 4번 탔다. 만약 구입한 표가 총 10개라면, 태형은 몇 장의 표를 남았을까?"
    },
    "443": {
        "question": "학교 베이크 세일을 위해 지민은 14개의 컵케이크를 만들었다. 만약 지민이가 컵케이크 중 6개를 팔고 그리고 17개를 더 만든다면, 지민은 얼마나 많은 컵케이크를 가지고 있을까요?"
    },
    "444": {
        "question": "올해 X의 가치는 16000달러로 지난해의 80%이다. 작년에 X의 가치는 얼마였습니까?"
    },
    "445": {
        "question": "휴식시간에 28명의 소녀와 35명의 소년들이 운동장에 있었다. 모두 몇 명의 아이들이 있었습니까?"
    },
    "446": {
        "question": "2와 15와 4를 모두 더하면?"
    },
    "447": {
        "question": "정국은 각 3개씩 있는 바인더로 야구 카드를 정리하고 있었다. 만약 정국이 바인더에 넣을 3개의 새로운 카드와 9개의 오래된 카드를 가지고 있다면, 그는 몇 개의 바인더를 사용해야 하나요?"
    },
    "448": {
        "question": "호석은 42개의 장난감을 가지고 있다. 호석은 25개의 장난감을 잃었습니다. 호석은 몇 개의 장난감을 가지고 있나요?"
    },
    "449": {
        "question": "레스토랑에서 각 성인 식사는 7달러이고 아이들은 무료로 먹는다. 만약 13명의 성인이 들어오고 9명의 아이들이라면, 모두 먹는데 얼마가 들겠는가?"
    },
    "450": {
        "question": "피자 가게의 주인은 팔린 각각의 피자에 대한 비용의 80%의 이윤을 만들기를 원한다. 만약 피자를 만드는데 8.5 달러가 든다면, 각 피자는 어떤 가격에 팔려야 하는가?"
    },
    "451": {
        "question": "은지는 그녀의 모든 오래된 책들을 팔기로 결심했다. 은지는 팔기 위해 33권의 책을 모았다. 은지는 시장에서 26권의 책을 팔았다. 은지는 지금 몇 권의 책을 가지고 있습니까?"
    },
    "452": {
        "question": "태형은 5개의 곤충을 가지고 있었지만, 완전한 수집에는 총 7개가 더 필요하다. 만약 한 곤충을 수집할 때 5달러가 든다면, 태형이 수집할 때 필요한 돈은 얼마일까?"
    },
    "453": {
        "question": "(가) 지역에는 5256명의 성인들과 2987명의 아이들이 있다. (가) 지역에는 얼마나 많은 사람들이 삽니까?"
    },
    "454": {
        "question": "0.125와 0.125와 0.7을 모두 더하면?"
    },
    "455": {
        "question": "은지는 5개의 테이블을 가지고 있었고, 5명의 여자와 3명의 남자가 각각의 테이블에 있었습니다. 은지는 총 몇 명의 손님이 있었습니까?"
    },
    "456": {
        "question": "유나는 쟁반을 집는 것을 돕고 있었습니다, 그러나 유나는 한 번에 오직 9개의 쟁반을 운반할 수 있었습니다. 만약 유나가 한 테이블에서 17개의 쟁반과 다른 테이블로부터 55개의 쟁반을 주워야 한다면, 그는 얼마나 많이 테이블에 다녀와야 할까요?"
    },
    "457": {
        "question": "397개의 나비가 있다. 각각의 나비들은 12개의 검은 점과 17개의 노란 점을 가지고 있습니다. 모두 몇 개의 검은 점들이 있나요?"
    },
    "458": {
        "question": "태형은 실험을 위해 두 조각의 금속의 무게를 쟀다. 철 조각은 11.16 파운드였고 알루미늄 조각은 0.83 파운드였다. 철의 조각이 알루미늄 조각보다 얼마나 더 무게가 나갔는가? 답을 소수점으로 작성하시오."
    },
    "459": {
        "question": "지민은 78개의 연필을 가지고 있다. 지민은 남준에게 44개의 연필을 준다. 지민은 연필을 몇 개 남습니까?"
    },
    "460": {
        "question": "할로윈을 위해 석진은 47조각의 사탕을 얻었다. 석진은 첫 날밤 25조각을 먹었고 석진은 남준에게 40조각을 더 주었다. 석진은 지금 몇 조각의 사탕을 가지고 있나요?"
    },
    "461": {
        "question": "태형은 2마리의 개를 가지고 있다. 매일, 한 개는 0.125g의 개 음식을 먹고 다른 개는 0.125g을 먹습니다. 두 개는 하루에 얼마나 많은 개 음식을 먹나요?"
    },
    "462": {
        "question": "은지는 카드 거래를 좋아한다. 은지는 카드 4갑을 각각 4.45 달러에 샀고 추가로 카드 한 갑을 6.06 달러에 샀다. 은지는 카드에 얼마를 썼는가?"
    },
    "463": {
        "question": "공원에는 현재 47개의 나무가 있다. 공원 직원들은 오늘 37개의 나무를 심을 것이고 내일 25개의 나무를 심을 것이다. 직원들이 일을 마치면 공원에는 얼마나 많은 나무가 있을까?"
    },
    "464": {
        "question": "남준은 민영의 집으로 시속 4km로 걸으면 2시간이 걸린다. 남준의 집과 민영의 집 사이의 거리는 얼마나 됩니까?"
    },
    "465": {
        "question": "태형은 여름에 잔디를 깎는 대가로 104달러를 벌었습니다. 만약 태형이 41달러를 썼다면, 태형이 남긴 돈으로 얼마나 많은 9달러 사과을 살 수 있었을까요?"
    },
    "466": {
        "question": "레스토랑에서 성인 2명과 어린이 5명이 함께 식사를 하러 왔다. 만약 모든 식사가 3달러라면 총 얼마를 계산해야할까?"
    },
    "467": {
        "question": "만약 정국이 10개의 회원권을 개당 175달러에 회원권을 산다면, 정국은 회원권을 사기 위해 얼마를 지출해야 합니까?"
    },
    "468": {
        "question": "3과 2와 10을 모두 더하면?"
    },
    "469": {
        "question": "남준은 지우개 8개를 가지고 있다. 은지는 남준에게 3개를 더 준다. 남준은 지우개를 몇 개 가지고 있을까요?"
    },
    "470": {
        "question": "현재 공원에는 4그루의 호두나무가 있다. 공원 직원들은 오늘 6그루의 호두나무를 더 심을 것이다. 직원들이 모두 심으면 공원에는 호두나무가 몇 그루나 될까요?"
    },
    "471": {
        "question": "상자 안에 있는 각각의 사과는 4달러입니다. 만약 상자가 총 8개의 사과를 가지고 있고 정국이가 3개의 사과를 제외한 모든 사과를 팔았다면, 정국이는 얼마나 많은 돈을 벌었을까요?"
    },
    "472": {
        "question": "유정은 75개의 알을 가지고 있고 석진은 17개의 알을 가지고 있다. 유정은 석진에게 70개의 알을 준다. 유정은 얼마나 많은 알을 가질까?"
    },
    "473": {
        "question": "윤기는 20권의 책을 가지고 있다. 민영은 21권의 책을 가지고 있다. 모두 몇 권의 책을 함께 가지고 있나요?"
    },
    "474": {
        "question": "(가) 지역의 야구팀은 31명의 새로운 선수들과 4명의 복귀 선수들을 가지고 있었다. 만약 코치가 선수들을 각 그룹에 7명의 선수들로 구성한다면, 얼마나 많은 그룹이 있을 것인가?"
    },
    "475": {
        "question": "은지는 오래된 겨울 옷을 풀고 있었다. 은지는 7개의 옷 상자를 발견했고 각각의 상자 안에는 3개의 스카프와 4개의 벙어리장갑이 있었다. 은지는 총 몇 조각의 겨울옷을 가지고 있었는가?"
    },
    "476": {
        "question": "민영은 10권의 책을 가지고 있다. 지민은 38권의 책을 가지고 있다. 모두 몇 권의 책을 함께 가지고 있나요?"
    },
    "477": {
        "question": "정국은 48097kg의 밀을 수확할 것이라고 생각한다. 정국은 한 묶음 당 684kg씩 밀을 나눌 때, 몇 묶음이 생길까요?"
    },
    "478": {
        "question": "은지는 지난달에 가게에 3번 갔다. 은지는 가게에 갈 때마다 7개의 땅콩을 산다. 은지는 지난 달에 얼마나 많은 땅콩을 샀습니까?"
    },
    "479": {
        "question": "석진은 10개의 비디오 게임을 가지고 있었지만 그 중 8개의 비디오 게임이 작동하지 않았다. 만약 석진이 작동하는 게임을 각각 6달러에 팔기를 원한다면, 얼마나 많은 돈을 벌 수 있을까?"
    },
    "480": {
        "question": "자동차는 하루에 50 달러와 km당 0.2 달러의 세금을 낸다. 5일간 자동차를 운행할 때 매일 32km을 주행하면, 총 얼마의 세금을 지불해야 하나요?"
    },
    "481": {
        "question": "(가) 지역의 야구팀은 12명의 새로운 선수들과 44명의 복귀 선수들을 가지고 있었다. 만약 코치가 선수들을 각 그룹마다 8명의 선수들을 함께 넣는다면, 얼마나 많은 그룹이 생길 것인가?"
    },
    "482": {
        "question": "현재 공원에는 7그루의 은행나무가 있다. 공원 직원들은 오늘 5그루의 은행나무와 내일 4그루의 은행나무들을 심을 것이다. 직원들이 일을 마치면 공원에는 몇 그루의 은행나무가 있을까?"
    },
    "483": {
        "question": "(가) 지역에 1426개의 집이 있었습니다. 추가로 (가) 지역에 2000개의 집을 지었습니다. (가) 지역에는 몇 개의 집이 더 있나요?"
    },
    "484": {
        "question": "서점에서 태형은 책 9권에 79달러를 냈다. 태형은 잔돈으로 16달러를 가졌다. 책 한 권당 가격은 얼마일까요?"
    },
    "485": {
        "question": "지민은 한 송이당 8달러씩 팔고 있었다. 호석이가 꽃 3송이와 다음 날 꽃 3송이를 더 샀다면, 호석이는 모두 얼마를 썼을까?"
    },
    "486": {
        "question": "34개의 연필과 49개의 크레파스가 서랍 안에 있다. 민영은 22개의 연필을 서랍에서 꺼냈다. 지금 서랍에 연필이 몇 자루나 있을까요?"
    },
    "487": {
        "question": "115개의 연필이 서랍 안에 있다. 윤기는 100개의 연필을 더 서랍 안에 두었다. 현재 서랍 안에 연필은 모두 몇 자루나 됩니까?"
    },
    "488": {
        "question": "25와 4167과 25를 모두 더하면?"
    },
    "489": {
        "question": "정국은 매년 11kg의 꽃을 수집한다. 정국은 여덟 살 입니다. 정국은 총 몇 kg의 꽃을 가지고 있나요?"
    },
    "490": {
        "question": "민영은 21달러를 저축했다. 만약 용돈으로 15달러를 더 받으면, 민영은 몇 개의 6달러의 장난감을 살 수 있을까?"
    },
    "491": {
        "question": "태형은 케이크를 굽고 있다. 케이크를 만드는데 밀가루 8컵을 원한다. 태형은 벌써 두 컵을 넣었다. 태형은 몇 개의 컵을 추가해야 합니까?"
    }
}